{
    "agency.txt": {
        "hash": "81a082be1ae1417e66e90112e41070ab",
        "last_modified": "2026-05-25T13:14:41+00:00",
        "version_int": 0
    },
    "calendar.txt": {
        "hash": "356e3ff06a840290f4b238c7c5e342a1",
        "last_modified": "2026-06-16T02:12:19+00:00",
        "version_int": 10
    },
    "calendar_dates.txt": {
        "hash": "6fadb8f2c389bdb85e1e9428ef504ceb",
        "last_modified": "2026-06-16T02:12:19+00:00",
        "version_int": 10
    },
    "fare_attributes.txt": {
        "hash": "e205ad05d08e9ec7577543a6e63a3baf",
        "last_modified": "2026-05-25T13:14:41+00:00",
        "version_int": 0
    },
    "fare_rules.txt": {
        "hash": "18d8f39bf420f026db5830dcba6643af",
        "last_modified": "2026-05-25T13:14:41+00:00",
        "version_int": 0
    },
    "feed_info.txt": {
        "hash": "ea9beb0f063df0b11866f9f8993b77b7",
        "last_modified": "2026-06-16T02:12:19+00:00",
        "version_int": 9
    },
    "routes.txt": {
        "hash": "903268320b87e98999a6f8639897ab51",
        "last_modified": "2026-06-12T02:00:05+00:00",
        "version_int": 3
    },
    "shapes.txt": {
        "hash": "7066c87c10f9dc3cdfc3d5820c6c2025",
        "last_modified": "2026-06-16T02:12:19+00:00",
        "version_int": 10
    },
    "stops.txt": {
        "hash": "6f8a2b01507f8605145e9d196e59c209",
        "last_modified": "2026-06-12T02:00:05+00:00",
        "version_int": 5
    },
    "stop_attributes.txt": {
        "hash": "2cd2aa2bd14c076bd9d2642829b326db",
        "last_modified": "2026-06-12T02:00:05+00:00",
        "version_int": 1
    },
    "stop_times.txt": {
        "hash": "3eb9da6e25d372dee53536257ec37acd",
        "last_modified": "2026-06-16T02:12:19+00:00",
        "version_int": 10
    },
    "timetables.txt": {
        "hash": "0e5dec0a4b273ae99ffe7a8dd05725f9",
        "last_modified": "2026-06-16T02:12:21+00:00",
        "version_int": 9
    },
    "timetable_pages.txt": {
        "hash": "0c9549fac85deb2e28287645a88716db",
        "last_modified": "2026-06-12T02:00:08+00:00",
        "version_int": 3
    },
    "timetable_stop_order.txt": {
        "hash": "89dfcc2334165f3dc47c7a8329d411f4",
        "last_modified": "2026-05-25T13:14:44+00:00",
        "version_int": 0
    },
    "trips.txt": {
        "hash": "88c28f9b6e3ec8534e6f65e7b463883c",
        "last_modified": "2026-06-16T02:12:21+00:00",
        "version_int": 10
    },
    "trips_booking.txt": {
        "hash": "ae84f0680d75f61200e9066cd2758fb9",
        "last_modified": "2026-05-25T13:14:44+00:00",
        "version_int": 0
    },
    "vehicles.txt": {
        "hash": "be85f382e3ffd99bd62a5f609c8af4a1",
        "last_modified": "2026-06-16T02:12:21+00:00",
        "version_int": 10
    },
    "vehicle_categories.txt": {
        "hash": "fd3d65b2d2a69c5c6224086a08e8f072",
        "last_modified": "2026-05-25T13:14:44+00:00",
        "version_int": 0
    }
}